README.rst
setup.py
phg/__init__.py
phg.egg-info/PKG-INFO
phg.egg-info/SOURCES.txt
phg.egg-info/dependency_links.txt
phg.egg-info/top_level.txt
scripts/phg