Metadata-Version: 1.1
Name: phg
Version: 2.0.0
Summary: Password hasher and generator
Home-page: https://github.com/hvnsweeting/phg
Author: Viet Hung Nguyen
Author-email: hvn@familug.org
License: MIT
Platform: UNKNOWN
Classifier: Environment :: Console
Classifier: Topic :: Terminals :: Terminal Emulators/X Terminals
